jupyterlab_telemetry_router/__init__.py
jupyterlab_telemetry_router/_version.py
jupyterlab_telemetry_router/application.py
jupyterlab_telemetry_router/handlers.py
jupyterlab_telemetry_router-0.1.27.data/data/etc/jupyter/jupyter_server_config.d/jupyterlab_telemetry_router.json
jupyterlab_telemetry_router-0.1.27.data/data/share/jupyter/labextensions/jupyterlab-telemetry-router/package.json
jupyterlab_telemetry_router-0.1.27.data/data/share/jupyter/labextensions/jupyterlab-telemetry-router/static/747.418af017b1ad995a1e39.js
jupyterlab_telemetry_router-0.1.27.data/data/share/jupyter/labextensions/jupyterlab-telemetry-router/static/763.e72ae0171e81b8ca7fc2.js
jupyterlab_telemetry_router-0.1.27.data/data/share/jupyter/labextensions/jupyterlab-telemetry-router/static/remoteEntry.7ef7b8000ffbed0efeb9.js
jupyterlab_telemetry_router-0.1.27.data/data/share/jupyter/labextensions/jupyterlab-telemetry-router/static/style.js
jupyterlab_telemetry_router-0.1.27.data/data/share/jupyter/labextensions/jupyterlab-telemetry-router/static/third-party-licenses.json
jupyterlab_telemetry_router-0.1.27.data/data/share/jupyter/labextensions/jupyterlab-telemetry-router/install.json
jupyterlab_telemetry_router-0.1.27.dist-info/METADATA
jupyterlab_telemetry_router-0.1.27.dist-info/WHEEL
jupyterlab_telemetry_router-0.1.27.dist-info/licenses/LICENSE
jupyterlab_telemetry_router-0.1.27.dist-info/RECORD
